garpix_notify/CHANGELOG.md
garpix_notify/CONTRIBUTING.md
garpix_notify/MANIFEST.in
garpix_notify/README.md
garpix_notify/README.rst
garpix_notify/__init__.py
garpix_notify/apps.py
garpix_notify/consumers.py
garpix_notify/exceptions.py
garpix_notify/routing.py
garpix_notify/serializers.py
garpix_notify/settings.py
garpix_notify/setup.py
garpix_notify/smtp.py
garpix_notify/urls.py
garpix_notify/views.py
garpix_notify/__pycache__/__init__.cpython-311.pyc
garpix_notify/__pycache__/__init__.cpython-38.pyc
garpix_notify/__pycache__/apps.cpython-311.pyc
garpix_notify/__pycache__/apps.cpython-38.pyc
garpix_notify/__pycache__/exceptions.cpython-38.pyc
garpix_notify/__pycache__/serializers.cpython-38.pyc
garpix_notify/__pycache__/settings.cpython-311.pyc
garpix_notify/__pycache__/settings.cpython-38.pyc
garpix_notify/__pycache__/urls.cpython-38.pyc
garpix_notify/__pycache__/views.cpython-38.pyc
garpix_notify/admin/__init__.py
garpix_notify/admin/category.py
garpix_notify/admin/config.py
garpix_notify/admin/fcm.py
garpix_notify/admin/file.py
garpix_notify/admin/log.py
garpix_notify/admin/notify.py
garpix_notify/admin/smtp.py
garpix_notify/admin/system_log.py
garpix_notify/admin/system_notify.py
garpix_notify/admin/template.py
garpix_notify/admin/user_list.py
garpix_notify/admin/user_list_participant.py
garpix_notify/admin/__pycache__/__init__.cpython-38.pyc
garpix_notify/admin/__pycache__/category.cpython-38.pyc
garpix_notify/admin/__pycache__/config.cpython-38.pyc
garpix_notify/admin/__pycache__/fcm.cpython-38.pyc
garpix_notify/admin/__pycache__/file.cpython-38.pyc
garpix_notify/admin/__pycache__/log.cpython-38.pyc
garpix_notify/admin/__pycache__/notify.cpython-38.pyc
garpix_notify/admin/__pycache__/smtp.cpython-38.pyc
garpix_notify/admin/__pycache__/system_log.cpython-38.pyc
garpix_notify/admin/__pycache__/system_notify.cpython-38.pyc
garpix_notify/admin/__pycache__/template.cpython-38.pyc
garpix_notify/admin/__pycache__/user_list.cpython-38.pyc
garpix_notify-5.16.3.dist-info/METADATA
garpix_notify-5.16.3.dist-info/WHEEL
garpix_notify-5.16.3.dist-info/top_level.txt
garpix_notify-5.16.3.dist-info/RECORD
