Metadata-Version: 2.1
Name: garpix-notify
Version: 5.16.3
Home-page: https://github.com/garpixcms/garpix_notify
Author: Garpix LTD
Author-email: info@garpix.com
License: MIT
Classifier: Development Status :: 4 - Beta
Classifier: Environment :: Web Environment
Classifier: Intended Audience :: Developers
Classifier: License :: OSI Approved :: MIT License
Classifier: Operating System :: OS Independent
Classifier: Programming Language :: Python
Classifier: Framework :: Django
Classifier: Programming Language :: Python :: 3.6
Classifier: Programming Language :: Python :: 3.7
Classifier: Programming Language :: Python :: 3.8
Requires-Dist: Django (>=1.11)
Requires-Dist: django-solo (>=1.1.3)
Requires-Dist: fcm-django (==0.3.11)
Requires-Dist: requests (>=2.18.4)
Requires-Dist: django-ckeditor (>=5.6.1)
Requires-Dist: python-telegram-bot (>=20.0)
Requires-Dist: viberbot (>=1.0.11)
Requires-Dist: django-uuslug (>=1.2.0)
Requires-Dist: Pillow (>=8.2.0)
Requires-Dist: celery (>=4.4.2)
Requires-Dist: redis (>=3.5.3)
Requires-Dist: channels (<=3.0.4,>=3.0.3)
Requires-Dist: channels-redis (==3.4.0)
Requires-Dist: asgiref (<=3.3.4,>=3.2.10)
Requires-Dist: twilio (==7.10.0)
Requires-Dist: typing-extensions (>=4.3.0)
Requires-Dist: djangorestframework (>=3.12.4)
Requires-Dist: garpix-utils (>=1.8.0)
Requires-Dist: rarfile (>=4.0)
Requires-Dist: unrar (>=0.4)
